frenchtext/__init__.py
frenchtext/_nbdev.py
frenchtext/chars.py
frenchtext/core.py
frenchtext/datasets.py
frenchtext/data/chars/charset-fr.csv
frenchtext/data/chars/charsetstats_norm.csv
frenchtext/data/chars/charsetstats_raw.csv
frenchtext/data/chars/combiningdiacritics.csv
frenchtext/data/chars/controlchars.csv
frenchtext/data/chars/cyrillic-greek-chars.csv
frenchtext/data/chars/latinletters.csv
frenchtext/data/chars/latinnumbers.csv
frenchtext/data/chars/latinsymbols.csv
frenchtext/data/chars/normalizedchars.csv
frenchtext/data/chars/unicode_blocks.csv
frenchtext/data/chars/unicode_categories.csv
frenchtext/data/chars/unicode_families.csv
frenchtext/data/chars/utf8-windows1252-errors.csv
frenchtext/data/chars/windows1252-iso8859-errors.csv
frenchtext/data/chars/windows1252-utf8-errors.csv
frenchtext/data/chars/stats/normalization.layer11.stats.csv
frenchtext/data/chars/stats/normalization.layer8.stats.csv
frenchtext/data/chars/stats/normalization.stats.csv
frenchtext/data/chars/stats/normalization.total.stats.csv
frenchtext/data/datasets/datasets.csv
frenchtext/data/datasets/download_info.csv
frenchtext-0.0.5.dist-info/LICENSE
frenchtext-0.0.5.dist-info/METADATA
frenchtext-0.0.5.dist-info/WHEEL
frenchtext-0.0.5.dist-info/entry_points.txt
frenchtext-0.0.5.dist-info/top_level.txt
frenchtext-0.0.5.dist-info/RECORD
