Metadata-Version: 2.1
Name: frenchtext
Version: 0.0.5
Summary: NLP library to process french text
Home-page: https://github.com/laurentprudhon/frenchtext
Author: Laurent Prudhon
Author-email: laurent.prudhon@hotmail.fr
License: Apache Software License 2.0
Keywords: NLP french text
Platform: UNKNOWN
Classifier: Development Status :: 4 - Beta
Classifier: Intended Audience :: Developers
Classifier: License :: OSI Approved :: Apache Software License
Classifier: Natural Language :: English
Classifier: Programming Language :: Python :: 3.6
Classifier: Programming Language :: Python :: 3.7
Classifier: Programming Language :: Python :: 3.8
Requires-Python: >=3.6
